idleuserextend/__init__.py
idleuserextend-0.0.3.dist-info/licenses/LICENSE
idleuserextend-0.0.3.dist-info/METADATA
idleuserextend-0.0.3.dist-info/WHEEL
idleuserextend-0.0.3.dist-info/entry_points.txt
idleuserextend-0.0.3.dist-info/top_level.txt
idleuserextend-0.0.3.dist-info/RECORD
